_realreq/__init__.py
_realreq/aliases.json
_realreq/display.py
_realreq/realreq.py
_realreq/std_lib.json
_realreq/requtils/__init__.py
_realreq/requtils/dependency_tree.py
realreq-0.7.4.dist-info/LICENSE
realreq-0.7.4.dist-info/METADATA
realreq-0.7.4.dist-info/WHEEL
realreq-0.7.4.dist-info/entry_points.txt
realreq-0.7.4.dist-info/top_level.txt
realreq-0.7.4.dist-info/RECORD
