Metadata-Version: 2.1
Name: realreq
Version: 0.7.4
Summary: CLI tool to gather dependencies for imports actually used by your code
Home-page: https://github.com/Calder-Ty/realreq
Author: Tyler Calder
Author-email: calder-ty@protonmail.com
Classifier: Programming Language :: Python :: 3.6
Classifier: Programming Language :: Python :: 3.7
Classifier: Programming Language :: Python :: 3.8
Classifier: Programming Language :: Python :: 3.9
Classifier: Programming Language :: Python :: 3.10
Classifier: Operating System :: POSIX :: Linux
Classifier: Development Status :: 4 - Beta
Classifier: License :: OSI Approved :: MIT License
Classifier: Topic :: Software Development :: Build Tools
Requires-Python: >=3.6
License-File: LICENSE
